jet_test/__init__.py
jet_test/checks.py
jet_test/classes.py
jet_test/main.py
jet_test/report.py
jet_test/runner.py
jet_test/seer.py
jet_test/ui.py
jet_test-0.0.3.dist-info/LICENSE
jet_test-0.0.3.dist-info/METADATA
jet_test-0.0.3.dist-info/WHEEL
jet_test-0.0.3.dist-info/entry_points.txt
jet_test-0.0.3.dist-info/top_level.txt
jet_test-0.0.3.dist-info/RECORD
