Metadata-Version: 2.1
Name: jet-test
Version: 0.0.3
Summary: Simple clean testing toolkit
Author-email: António Leitão <aleitao@novaims.unl.pt>
Project-URL: Homepage, https://github.com/Antonio-Leitao/jet
Classifier: Programming Language :: Python :: 3
Classifier: License :: OSI Approved :: MIT License
Classifier: Operating System :: OS Independent
Requires-Python: >=3.10
License-File: LICENSE
Requires-Dist: rich (>=12.6.0)
